movie_collection/__init__.py
movie_collection/funcs.py
movie_collection-0.1.1.dist-info/DESCRIPTION.rst
movie_collection-0.1.1.dist-info/METADATA
movie_collection-0.1.1.dist-info/RECORD
movie_collection-0.1.1.dist-info/WHEEL
movie_collection-0.1.1.dist-info/metadata.json
movie_collection-0.1.1.dist-info/top_level.txt
