Metadata-Version: 2.0
Name: movie-collection
Version: 0.1.1
Summary: Create dvd collection and calculate runtime
Home-page: UNKNOWN
Author: Juliana Borst
Author-email: j_borst1@pacific.edu
License: UNKNOWN
Keywords: movie library dvd length
Platform: UNKNOWN
Classifier: Programming Language :: Python :: 3.5
Classifier: Natural Language :: English
